victron_ble/__init__.py
victron_ble/cli.py
victron_ble/exceptions.py
victron_ble/py.typed
victron_ble/scanner.py
victron_ble/devices/__init__.py
victron_ble/devices/ac_charger.py
victron_ble/devices/base.py
victron_ble/devices/battery_monitor.py
victron_ble/devices/battery_sense.py
victron_ble/devices/dc_energy_meter.py
victron_ble/devices/dcdc_converter.py
victron_ble/devices/inverter.py
victron_ble/devices/lynx_smart_bms.py
victron_ble/devices/orion_xs.py
victron_ble/devices/smart_battery_protect.py
victron_ble/devices/smart_lithium.py
victron_ble/devices/solar_charger.py
victron_ble/devices/vebus.py
victron_ble-0.9.2.dist-info/licenses/LICENSE
victron_ble-0.9.2.dist-info/METADATA
victron_ble-0.9.2.dist-info/WHEEL
victron_ble-0.9.2.dist-info/entry_points.txt
victron_ble-0.9.2.dist-info/top_level.txt
victron_ble-0.9.2.dist-info/RECORD
